hmrc/__init__.py
hmrc/api/__init__.py
hmrc/api/client.py
hmrc/api/data.py
hmrc/api/defraud.py
hmrc/api/hello.py
hmrc/api/testuser.py
hmrc/api/vat.py
hmrc/auth/__init__.py
hmrc/auth/session.py
hmrc/auth/testuser.py
hmrc/auth/token.py
hmrc/cli/__init__.py
hmrc/cli/base.py
hmrc/cli/hello.py
hmrc/cli/registry.py
hmrc/cli/vat.py
hmrc/plugins/__init__.py
hmrc/plugins/csv.py
hmrc/plugins/excel.py
hmrc/plugins/tabular.py
test/__init__.py
test/hmrctest.py
test/test_defraud.py
test/test_doc.py
test/test_hello.py
test/test_refresh.py
test/test_token.py
test/test_vat.py
hmrc-1.1.3.dist-info/METADATA
hmrc-1.1.3.dist-info/WHEEL
hmrc-1.1.3.dist-info/entry_points.txt
hmrc-1.1.3.dist-info/top_level.txt
hmrc-1.1.3.dist-info/RECORD
