Metadata-Version: 2.1
Name: hmrc
Version: 1.1.3
Summary: HMRC API client library
Home-page: https://github.com/mcb30/hmrc
Author: Michael Brown
Author-email: mbrown@fensystems.co.uk
License: GPLv2+
Platform: UNKNOWN
Classifier: Development Status :: 2 - Pre-Alpha
Classifier: Environment :: Console
Classifier: Environment :: Web Environment
Classifier: Intended Audience :: Developers
Classifier: Intended Audience :: Financial and Insurance Industry
Classifier: License :: OSI Approved :: GNU General Public License v2 or later (GPLv2+)
Classifier: Programming Language :: Python :: 3
Classifier: Topic :: Office/Business :: Financial
Classifier: Topic :: Software Development :: Libraries
Requires-Dist: iso8601
Requires-Dist: lxml
Requires-Dist: parsedatetime
Requires-Dist: psutil
Requires-Dist: python-dateutil
Requires-Dist: requests
Requires-Dist: requests-oauthlib
Requires-Dist: setuptools
Requires-Dist: simplejson
Requires-Dist: uritemplate
Requires-Dist: urllib3
Requires-Dist: xlrd
